{"entries":[{"id":"custom_biome_definition","name":"custom_biome_definition","description":"Define a custom biome with colors and climate settings","color":"#F57C00","icon":"mdi:pine-tree-box","className":"btcrenaud.custombiome.entries.manifest.CustomBiomeDefinitionEntry","extension":"CustomBiome","tags":["custombiome","manifest","definition","manifest","entry"],"dataBlueprint":{"kind":"object","fields":{"id":{"kind":"primitive","type":"string"},"name":{"kind":"primitive","type":"string"},"biomeId":{"kind":"primitive","modifiers":[{"name":"help","data":"Unique biome ID (lowercase, no spaces, use underscores)"}],"type":"string"},"namespace":{"kind":"primitive","modifiers":[{"name":"help","data":"Namespace for the biome key (default: typewriter)"}],"type":"string"},"baseBiome":{"kind":"primitive","modifiers":[{"name":"help","data":"Base vanilla biome to inherit properties from (e.g., 'minecraft:plains', 'minecraft:forest')"}],"type":"string"},"temperature":{"kind":"primitive","modifiers":[{"name":"help","data":"Temperature value (0.0 = cold/snowy, 0.5 = temperate, 2.0 = hot). Leave empty to inherit from base biome."}],"type":"string"},"downfall":{"kind":"primitive","modifiers":[{"name":"help","data":"Downfall/humidity value (0.0 = dry, 1.0 = wet/rainy). Leave empty to inherit from base biome."}],"type":"string"},"fogColor":{"kind":"primitive","modifiers":[{"name":"help","data":"Fog color in hex format (#RRGGBB). Leave empty to inherit from base biome."}],"type":"string"},"waterColor":{"kind":"primitive","modifiers":[{"name":"help","data":"Water color in hex format (#RRGGBB). Leave empty to inherit from base biome."}],"type":"string"},"waterFogColor":{"kind":"primitive","modifiers":[{"name":"help","data":"Underwater fog color in hex format (#RRGGBB). Leave empty to inherit from base biome."}],"type":"string"},"skyColor":{"kind":"primitive","modifiers":[{"name":"help","data":"Sky color in hex format (#RRGGBB). Leave empty to inherit from base biome."}],"type":"string"},"foliageColor":{"kind":"primitive","modifiers":[{"name":"help","data":"Foliage/leaf color in hex format (#RRGGBB). Leave empty to inherit from base biome."}],"type":"string"},"grassColor":{"kind":"primitive","modifiers":[{"name":"help","data":"Grass color in hex format (#RRGGBB). Leave empty to inherit from base biome."}],"type":"string"},"dryFoliageColor":{"kind":"primitive","modifiers":[{"name":"help","data":"Dry foliage color for badlands/savanna in hex format (#RRGGBB). Leave empty to inherit from base biome."}],"type":"string"},"sunriseSunsetColor":{"kind":"primitive","modifiers":[{"name":"help","data":"Sunrise/sunset sky tint color in hex format (#RRGGBB). Leave empty to inherit from base biome."}],"type":"string"},"cloudColor":{"kind":"primitive","modifiers":[{"name":"help","data":"Cloud color in hex format (#RRGGBB). Leave empty to inherit from base biome."}],"type":"string"},"skyLightColor":{"kind":"primitive","modifiers":[{"name":"help","data":"Skylight color tint in hex format (#RRGGBB). Leave empty to inherit from base biome."}],"type":"string"},"fogStartDistance":{"kind":"primitive","modifiers":[{"name":"help","data":"Distance where fog starts"}],"type":"double"},"fogEndDistance":{"kind":"primitive","modifiers":[{"name":"help","data":"Distance where fog ends"}],"type":"double"},"skyFogEndDistance":{"kind":"primitive","modifiers":[{"name":"help","data":"Distance where sky fog ends"}],"type":"double"},"waterFogStartDistance":{"kind":"primitive","modifiers":[{"name":"help","data":"Distance where water fog starts"}],"type":"double"},"waterFogEndDistance":{"kind":"primitive","modifiers":[{"name":"help","data":"Distance where water fog ends"}],"type":"double"},"cloudFogEndDistance":{"kind":"primitive","modifiers":[{"name":"help","data":"Distance where cloud fog ends"}],"type":"double"},"cloudHeight":{"kind":"primitive","modifiers":[{"name":"help","data":"Height of the clouds"}],"type":"double"},"skyLightFactor":{"kind":"primitive","modifiers":[{"name":"help","data":"Multiplier for sky light brightness"}],"type":"double"},"sunAngle":{"kind":"primitive","modifiers":[{"name":"help","data":"Sun angle (0.0 = overhead)"}],"type":"double"},"moonAngle":{"kind":"primitive","modifiers":[{"name":"help","data":"Moon angle"}],"type":"double"},"starAngle":{"kind":"primitive","modifiers":[{"name":"help","data":"Star angle"}],"type":"double"},"starBrightness":{"kind":"primitive","modifiers":[{"name":"help","data":"Star brightness"}],"type":"double"},"moonPhase":{"kind":"primitive","modifiers":[{"name":"help","data":"Moon phase (full_moon, waning_gibbous, etc)"}],"type":"string"}}},"contextKeys":[],"modifiers":[]},{"id":"apply_biome_action","name":"apply_biome_action","description":"Apply a biome to a location with optional radius","color":"#1E88E5","icon":"mdi:pine-tree","className":"btcrenaud.custombiome.entries.action.ApplyBiomeActionEntry","extension":"CustomBiome","tags":["action","triggerable","trigger","entry"],"dataBlueprint":{"kind":"object","fields":{"id":{"kind":"primitive","type":"string"},"name":{"kind":"primitive","type":"string"},"triggers":{"kind":"list","modifiers":[{"name":"help","data":"The entries that will be fired after this entry."},{"name":"help","data":"The entries that will be fired after this entry."}],"type":{"kind":"custom","modifiers":[{"name":"entry","data":"triggerable"}],"editor":"ref","shape":{"kind":"primitive","type":"string"}}},"criteria":{"kind":"list","modifiers":[{"name":"help","data":"The criteria that must be met before this entry is triggered"},{"name":"help","data":"The criteria that must be met before this entry is triggered"}],"type":{"kind":"object","fields":{"fact":{"kind":"custom","modifiers":[{"name":"entry","data":"readable-fact"},{"name":"help","data":"The fact to check before triggering the entry"}],"editor":"ref","shape":{"kind":"primitive","type":"string"}},"operator":{"kind":"enum","modifiers":[{"name":"help","data":"The operator to use when comparing the fact value to the criteria value"}],"values":["==","<",">","<=",">=","!="]},"value":{"kind":"custom","modifiers":[{"name":"help","data":"The value to compare the fact value to"}],"default":0,"editor":"var","shape":{"kind":"primitive","modifiers":[{"name":"negative","data":null}],"type":"integer"}}}}},"modifiers":{"kind":"list","modifiers":[{"name":"help","data":"The modifiers that will be applied when this entry is triggered"},{"name":"help","data":"The modifiers that will be applied when this entry is triggered"}],"type":{"kind":"object","fields":{"fact":{"kind":"custom","modifiers":[{"name":"entry","data":"writable-fact"},{"name":"help","data":"The fact to modify after the entry is completed"}],"editor":"ref","shape":{"kind":"primitive","type":"string"}},"operator":{"kind":"enum","modifiers":[{"name":"help","data":"The operator to use when modifying the fact value"}],"values":["=","+","-","*"]},"value":{"kind":"custom","modifiers":[{"name":"help","data":"The value to modify the fact value by"}],"default":0,"editor":"var","shape":{"kind":"primitive","modifiers":[{"name":"negative","data":null}],"type":"integer"}}}}},"biome":{"kind":"custom","modifiers":[{"name":"help","data":"Biome identifier (e.g., 'minecraft:plains' or 'typewriter:my_biome')"}],"default":"","editor":"var","shape":{"kind":"primitive","type":"string"}},"radius":{"kind":"custom","modifiers":[{"name":"help","data":"Radius in blocks around the player's location (0 = single column)"}],"default":0,"editor":"var","shape":{"kind":"primitive","type":"integer"}},"atPlayerLocation":{"kind":"primitive","modifiers":[{"name":"help","data":"If true, applies at player's location. If false, requires a target location."}],"type":"boolean"}}},"contextKeys":[],"modifiers":[]},{"id":"refresh_biome_chunks_action","name":"refresh_biome_chunks_action","description":"Refresh biome data for chunks around the player","color":"#1E88E5","icon":"mdi:refresh","className":"btcrenaud.custombiome.entries.action.RefreshBiomeChunksActionEntry","extension":"CustomBiome","tags":["action","triggerable","trigger","entry"],"dataBlueprint":{"kind":"object","fields":{"id":{"kind":"primitive","type":"string"},"name":{"kind":"primitive","type":"string"},"triggers":{"kind":"list","modifiers":[{"name":"help","data":"The entries that will be fired after this entry."},{"name":"help","data":"The entries that will be fired after this entry."}],"type":{"kind":"custom","modifiers":[{"name":"entry","data":"triggerable"}],"editor":"ref","shape":{"kind":"primitive","type":"string"}}},"criteria":{"kind":"list","modifiers":[{"name":"help","data":"The criteria that must be met before this entry is triggered"},{"name":"help","data":"The criteria that must be met before this entry is triggered"}],"type":{"kind":"object","fields":{"fact":{"kind":"custom","modifiers":[{"name":"entry","data":"readable-fact"},{"name":"help","data":"The fact to check before triggering the entry"}],"editor":"ref","shape":{"kind":"primitive","type":"string"}},"operator":{"kind":"enum","modifiers":[{"name":"help","data":"The operator to use when comparing the fact value to the criteria value"}],"values":["==","<",">","<=",">=","!="]},"value":{"kind":"custom","modifiers":[{"name":"help","data":"The value to compare the fact value to"}],"default":0,"editor":"var","shape":{"kind":"primitive","modifiers":[{"name":"negative","data":null}],"type":"integer"}}}}},"modifiers":{"kind":"list","modifiers":[{"name":"help","data":"The modifiers that will be applied when this entry is triggered"},{"name":"help","data":"The modifiers that will be applied when this entry is triggered"}],"type":{"kind":"object","fields":{"fact":{"kind":"custom","modifiers":[{"name":"entry","data":"writable-fact"},{"name":"help","data":"The fact to modify after the entry is completed"}],"editor":"ref","shape":{"kind":"primitive","type":"string"}},"operator":{"kind":"enum","modifiers":[{"name":"help","data":"The operator to use when modifying the fact value"}],"values":["=","+","-","*"]},"value":{"kind":"custom","modifiers":[{"name":"help","data":"The value to modify the fact value by"}],"default":0,"editor":"var","shape":{"kind":"primitive","modifiers":[{"name":"negative","data":null}],"type":"integer"}}}}},"chunkRadius":{"kind":"custom","modifiers":[{"name":"help","data":"Chunk radius to refresh around the player (default: 5)"}],"default":0,"editor":"var","shape":{"kind":"primitive","type":"integer"}}}},"contextKeys":[],"modifiers":[]},{"id":"enter_biome_event","name":"enter_biome_event","description":"Triggered when a player enters a biome","color":"#FBB612","icon":"mdi:pine-tree","className":"btcrenaud.custombiome.entries.event.EnterBiomeEventEntry","extension":"CustomBiome","tags":["event","trigger","entry"],"dataBlueprint":{"kind":"object","fields":{"id":{"kind":"primitive","type":"string"},"name":{"kind":"primitive","type":"string"},"triggers":{"kind":"list","modifiers":[{"name":"help","data":"The entries that will be fired after this entry."},{"name":"help","data":"The entries that will be fired after this entry."}],"type":{"kind":"custom","modifiers":[{"name":"entry","data":"triggerable"}],"editor":"ref","shape":{"kind":"primitive","type":"string"}}},"biomes":{"kind":"list","modifiers":[{"name":"help","data":"Biome identifiers to trigger on (empty = any biome). Examples: 'minecraft:plains', 'typewriter:my_biome'"}],"type":{"kind":"primitive","type":"string"}},"ignoreMissing":{"kind":"primitive","modifiers":[{"name":"help","data":"If true, ignore missing biome identifiers instead of throwing errors"}],"type":"boolean"}}},"contextKeys":[{"name":"BIOME_ID","klassName":"btcrenaud.custombiome.entries.event.BiomeEventContextKeys","blueprint":{"kind":"primitive","type":"string"}},{"name":"BIOME_NAME","klassName":"btcrenaud.custombiome.entries.event.BiomeEventContextKeys","blueprint":{"kind":"primitive","type":"string"}},{"name":"PREVIOUS_BIOME_ID","klassName":"btcrenaud.custombiome.entries.event.BiomeEventContextKeys","blueprint":{"kind":"primitive","type":"string"}},{"name":"PREVIOUS_BIOME_NAME","klassName":"btcrenaud.custombiome.entries.event.BiomeEventContextKeys","blueprint":{"kind":"primitive","type":"string"}},{"name":"IS_CUSTOM_BIOME","klassName":"btcrenaud.custombiome.entries.event.BiomeEventContextKeys","blueprint":{"kind":"primitive","type":"boolean"}}],"modifiers":[]},{"id":"leave_biome_event","name":"leave_biome_event","description":"Triggered when a player leaves a biome","color":"#FBB612","icon":"mdi:pine-tree-off","className":"btcrenaud.custombiome.entries.event.LeaveBiomeEventEntry","extension":"CustomBiome","tags":["event","trigger","entry"],"dataBlueprint":{"kind":"object","fields":{"id":{"kind":"primitive","type":"string"},"name":{"kind":"primitive","type":"string"},"triggers":{"kind":"list","modifiers":[{"name":"help","data":"The entries that will be fired after this entry."},{"name":"help","data":"The entries that will be fired after this entry."}],"type":{"kind":"custom","modifiers":[{"name":"entry","data":"triggerable"}],"editor":"ref","shape":{"kind":"primitive","type":"string"}}},"biomes":{"kind":"list","modifiers":[{"name":"help","data":"Biome identifiers to trigger when leaving (empty = any biome). Examples: 'minecraft:plains', 'typewriter:my_biome'"}],"type":{"kind":"primitive","type":"string"}},"ignoreMissing":{"kind":"primitive","modifiers":[{"name":"help","data":"If true, ignore missing biome identifiers instead of throwing errors"}],"type":"boolean"}}},"contextKeys":[{"name":"BIOME_ID","klassName":"btcrenaud.custombiome.entries.event.BiomeEventContextKeys","blueprint":{"kind":"primitive","type":"string"}},{"name":"BIOME_NAME","klassName":"btcrenaud.custombiome.entries.event.BiomeEventContextKeys","blueprint":{"kind":"primitive","type":"string"}},{"name":"PREVIOUS_BIOME_ID","klassName":"btcrenaud.custombiome.entries.event.BiomeEventContextKeys","blueprint":{"kind":"primitive","type":"string"}},{"name":"PREVIOUS_BIOME_NAME","klassName":"btcrenaud.custombiome.entries.event.BiomeEventContextKeys","blueprint":{"kind":"primitive","type":"string"}},{"name":"IS_CUSTOM_BIOME","klassName":"btcrenaud.custombiome.entries.event.BiomeEventContextKeys","blueprint":{"kind":"primitive","type":"boolean"}}],"modifiers":[]},{"id":"player_biome_fact","name":"player_biome_fact","description":"Expose the player's current biome as a fact value","color":"#5843E6","icon":"mdi:pine-tree","className":"btcrenaud.custombiome.entries.fact.PlayerBiomeFactEntry","extension":"CustomBiome","tags":["readable-fact","fact","placeholder","static","entry","entry"],"dataBlueprint":{"kind":"object","fields":{"id":{"kind":"primitive","type":"string"},"name":{"kind":"primitive","type":"string"},"comment":{"kind":"primitive","modifiers":[{"name":"help","data":"A comment to keep track of what this fact is used for."},{"name":"multiline","data":null},{"name":"help","data":"A comment to keep track of what this fact is used for."},{"name":"multiline","data":null}],"type":"string"},"group":{"kind":"custom","modifiers":[{"name":"entry","data":"group"},{"name":"help","data":"If left empty, every player has its own group."},{"name":"help","data":"If left empty, every player has its own group."}],"editor":"ref","shape":{"kind":"primitive","type":"string"}},"mode":{"kind":"enum","modifiers":[{"name":"help","data":"Mode for determining the fact value"}],"values":["BOOLEAN","CODE","HASH"]},"biomes":{"kind":"list","modifiers":[{"name":"help","data":"Biome identifiers for BOOLEAN mode. Returns 1 if player is in any of these biomes, 0 otherwise."}],"type":{"kind":"primitive","type":"string"}},"codes":{"kind":"map","modifiers":[{"name":"help","data":"Biome to code mapping for CODE mode. Returns the code for the current biome."}],"key":{"kind":"primitive","type":"string"},"value":{"kind":"primitive","type":"integer"}},"defaultCode":{"kind":"primitive","modifiers":[{"name":"help","data":"Default code to return if current biome is not in the mapping"}],"type":"integer"},"ignoreMissing":{"kind":"primitive","modifiers":[{"name":"help","data":"If true, ignore missing biome identifiers instead of throwing errors"}],"type":"boolean"}}},"contextKeys":[],"modifiers":[]},{"id":"is_in_custom_biome_fact","name":"is_in_custom_biome_fact","description":"Returns 1 if player is in a custom biome, 0 otherwise","color":"#5843E6","icon":"mdi:pine-tree-box","className":"btcrenaud.custombiome.entries.fact.IsInCustomBiomeFactEntry","extension":"CustomBiome","tags":["readable-fact","fact","placeholder","static","entry","entry"],"dataBlueprint":{"kind":"object","fields":{"id":{"kind":"primitive","type":"string"},"name":{"kind":"primitive","type":"string"},"comment":{"kind":"primitive","modifiers":[{"name":"help","data":"A comment to keep track of what this fact is used for."},{"name":"multiline","data":null},{"name":"help","data":"A comment to keep track of what this fact is used for."},{"name":"multiline","data":null}],"type":"string"},"group":{"kind":"custom","modifiers":[{"name":"entry","data":"group"},{"name":"help","data":"If left empty, every player has its own group."},{"name":"help","data":"If left empty, every player has its own group."}],"editor":"ref","shape":{"kind":"primitive","type":"string"}}}},"contextKeys":[],"modifiers":[]},{"id":"custom_biome_count_fact","name":"custom_biome_count_fact","description":"Returns the number of registered custom biomes","color":"#5843E6","icon":"mdi:counter","className":"btcrenaud.custombiome.entries.fact.CustomBiomeCountFactEntry","extension":"CustomBiome","tags":["readable-fact","fact","placeholder","static","entry","entry"],"dataBlueprint":{"kind":"object","fields":{"id":{"kind":"primitive","type":"string"},"name":{"kind":"primitive","type":"string"},"comment":{"kind":"primitive","modifiers":[{"name":"help","data":"A comment to keep track of what this fact is used for."},{"name":"multiline","data":null},{"name":"help","data":"A comment to keep track of what this fact is used for."},{"name":"multiline","data":null}],"type":"string"},"group":{"kind":"custom","modifiers":[{"name":"entry","data":"group"},{"name":"help","data":"If left empty, every player has its own group."},{"name":"help","data":"If left empty, every player has its own group."}],"editor":"ref","shape":{"kind":"primitive","type":"string"}}}},"contextKeys":[],"modifiers":[]},{"id":"biome_audience","name":"biome_audience","description":"Filter players based on the biome they are standing in","color":"#4CAF50","icon":"mdi:pine-tree","className":"btcrenaud.custombiome.entries.audience.BiomeAudienceEntry","extension":"CustomBiome","tags":["audience_filter","audience","manifest","placeholder","entry","entry"],"dataBlueprint":{"kind":"object","fields":{"id":{"kind":"primitive","type":"string"},"name":{"kind":"primitive","type":"string"},"children":{"kind":"list","type":{"kind":"custom","modifiers":[{"name":"entry","data":"audience"}],"editor":"ref","shape":{"kind":"primitive","type":"string"}}},"biomes":{"kind":"list","modifiers":[{"name":"help","data":"Biome identifiers to filter on. Examples: 'minecraft:plains', 'typewriter:my_biome'"}],"type":{"kind":"primitive","type":"string"}},"ignoreMissing":{"kind":"primitive","modifiers":[{"name":"help","data":"If true, ignore missing biome identifiers instead of throwing errors"}],"type":"boolean"},"customBiomesOnly":{"kind":"primitive","modifiers":[{"name":"help","data":"If true, only include players in custom biomes (ignores biome list)"}],"type":"boolean"},"inverted":{"kind":"primitive","modifiers":[{"name":"help","data":"The audience will be the players that do not match the criteria."},{"name":"help","data":"The audience will be the players that do not match the criteria."}],"type":"boolean"}}},"contextKeys":[],"modifiers":[]},{"id":"current_biome_variable","name":"current_biome_variable","description":"Returns the player's current biome name","color":"#4CAF50","icon":"mdi:pine-tree","className":"btcrenaud.custombiome.entries.variable.CurrentBiomeVariableEntry","extension":"CustomBiome","tags":["variable","variable","static","entry"],"dataBlueprint":{"kind":"object","fields":{"id":{"kind":"primitive","type":"string"},"name":{"kind":"primitive","type":"string"},"format":{"kind":"enum","modifiers":[{"name":"help","data":"Format for the output: ID returns 'namespace:key', NAME returns readable name"}],"values":["ID","NAME","KEY","NAMESPACE"]}}},"contextKeys":[],"modifiers":[]},{"id":"biome_property_variable","name":"biome_property_variable","description":"Returns a property of the player's current biome","color":"#4CAF50","icon":"mdi:thermometer","className":"btcrenaud.custombiome.entries.variable.BiomePropertyVariableEntry","extension":"CustomBiome","tags":["variable","variable","static","entry"],"dataBlueprint":{"kind":"object","fields":{"id":{"kind":"primitive","type":"string"},"name":{"kind":"primitive","type":"string"},"property":{"kind":"enum","modifiers":[{"name":"help","data":"Which property to return"}],"values":["IS_CUSTOM","TEMPERATURE","DOWNFALL","BASE_BIOME"]}}},"contextKeys":[],"modifiers":[]},{"id":"custom_biome_list_variable","name":"custom_biome_list_variable","description":"Returns a list of registered custom biomes","color":"#4CAF50","icon":"mdi:format-list-bulleted","className":"btcrenaud.custombiome.entries.variable.CustomBiomeListVariableEntry","extension":"CustomBiome","tags":["variable","variable","static","entry"],"dataBlueprint":{"kind":"object","fields":{"id":{"kind":"primitive","type":"string"},"name":{"kind":"primitive","type":"string"},"separator":{"kind":"primitive","modifiers":[{"name":"help","data":"Separator between biome names (default: ', ')"}],"type":"string"},"format":{"kind":"enum","modifiers":[{"name":"help","data":"Format for each biome: ID or NAME"}],"values":["ID","NAME","KEY","NAMESPACE"]}}},"contextKeys":[],"modifiers":[]}],"entryListeners":[{"entryBlueprintId":"enter_biome_event","entryClassName":"btcrenaud.custombiome.entries.event.EnterBiomeEventEntry","className":"btcrenaud.custombiome.entries.event.BiomeEventsKt","methodName":"onPlayerMoveEnterBiome","priority":"NORMAL","ignoreCancelled":false,"arguments":["org.bukkit.event.player.PlayerMoveEvent","com.typewritermc.core.entries.Query"]},{"entryBlueprintId":"leave_biome_event","entryClassName":"btcrenaud.custombiome.entries.event.LeaveBiomeEventEntry","className":"btcrenaud.custombiome.entries.event.BiomeEventsKt","methodName":"onPlayerMoveLeaveBiome","priority":"NORMAL","ignoreCancelled":false,"arguments":["org.bukkit.event.player.PlayerMoveEvent","com.typewritermc.core.entries.Query"]}],"typewriterCommands":[{"className":"btcrenaud.custombiome.command.BiomeCommandKt","methodName":"biomeCommand"}],"dependencyInjections":[{"kind":"class","className":"btcrenaud.custombiome.CustomBiomeInitializer","type":"singleton"},{"kind":"class","className":"btcrenaud.custombiome.registry.CustomBiomeRegistry","type":"singleton"},{"kind":"class","className":"btcrenaud.custombiome.placeholder.CustomBiomePlaceholders","type":"singleton"},{"kind":"class","className":"btcrenaud.custombiome.service.CustomBiomeLifecycleService","type":"singleton"}],"globalContextKeys":[],"extension":{"name":"CustomBiome","shortDescription":"Create and manage custom biomes with full color and climate customization.","description":"Typewriter extension module providing additional entries for the Typewriter plugin ecosystem. Supports Paper and Folia server platforms with full feature parity. This module extends the core functionality with specialized entries. Compatible with the official Typewriter engine and designed for standalone use.","engineVersion":"0.9.0-beta-174","channel":"BETA","paper":{},"pluginVersion":"2.1.0","version":"0.0.3","namespace":"custombiome","dependencies":[]}}